simpleobject.py
simpleobject-1.0.5.dist-info/LICENSE
simpleobject-1.0.5.dist-info/METADATA
simpleobject-1.0.5.dist-info/WHEEL
simpleobject-1.0.5.dist-info/top_level.txt
simpleobject-1.0.5.dist-info/RECORD
