Metadata-Version: 2.1
Name: simpleobject
Version: 1.0.5
Summary: Simple json serializable object
Home-page: https://github.com/GabrieleMaurina/simpleobject
Author: Gabriele Maurina
Author-email: gabrielemaurina95@gmail.com
License: MIT
Platform: UNKNOWN
Classifier: Programming Language :: Python :: 3
Classifier: License :: OSI Approved :: MIT License
Classifier: Operating System :: OS Independent
Requires-Python: >=3.8
License-File: LICENSE
